openesm/__init__.py
openesm/get_dataset.py
openesm/list_datasets.py
openesm/utils.py
openesm/zenodo.py
openesm-0.1.2.dist-info/METADATA
openesm-0.1.2.dist-info/WHEEL
openesm-0.1.2.dist-info/licenses/LICENSE
openesm-0.1.2.dist-info/RECORD
